[
  {
    "id": "a6cf2969-7852-4d34-943b-1e77241512ec",
    "suite": "output",
    "suiteLabel": "Output",
    "requestedAt": "2025-10-02T02:09:14.017511+00:00",
    "generatedAt": "2025-10-02T02:09:14.016286+00:00",
    "summary": {
      "total": 4,
      "success": 4,
      "failed": 0
    },
    "benchmarkCount": 4,
    "failed": 0,
    "success": 4,
    "status": "success"
  },
  {
    "id": "6abae964-6279-400b-80f0-88c42479fe4e",
    "suite": "crisis",
    "suiteLabel": "Crisis",
    "requestedAt": "2025-10-02T02:09:08.817237+00:00",
    "generatedAt": "2025-10-02T02:09:08.816454+00:00",
    "summary": {
      "total": 1,
      "success": 0,
      "failed": 1
    },
    "benchmarkCount": 1,
    "failed": 1,
    "success": 0,
    "status": "needs_attention"
  },
  {
    "id": "849911c5-2958-4a12-89b4-7c5b1514329c",
    "suite": "custom",
    "suiteLabel": "Custom",
    "requestedAt": "2025-10-02T02:09:07.348579+00:00",
    "generatedAt": "2025-10-02T02:09:07.347476+00:00",
    "summary": {
      "total": 3,
      "success": 3,
      "failed": 0
    },
    "benchmarkCount": 3,
    "failed": 0,
    "success": 3,
    "status": "success"
  },
  {
    "id": "57a6e953-a956-44a8-a3bc-825a7ba3408b",
    "suite": "output",
    "suiteLabel": "Output",
    "requestedAt": "2025-10-02T02:09:05.661737+00:00",
    "generatedAt": "2025-10-02T02:09:05.660364+00:00",
    "summary": {
      "total": 4,
      "success": 4,
      "failed": 0
    },
    "benchmarkCount": 4,
    "failed": 0,
    "success": 4,
    "status": "success"
  },
  {
    "id": "9ffb6d27-9163-4dd3-b0f3-8970649d43d6",
    "suite": "all",
    "suiteLabel": "All",
    "requestedAt": "2025-10-02T02:09:02.884170+00:00",
    "generatedAt": "2025-10-02T02:09:02.852508+00:00",
    "summary": {
      "total": 8,
      "success": 7,
      "failed": 1
    },
    "benchmarkCount": 8,
    "failed": 1,
    "success": 7,
    "status": "needs_attention"
  },
  {
    "id": "a5ddc089-be68-48d9-ba88-48f9dd65811d",
    "suite": "all",
    "requestedAt": "2025-10-02T02:04:28.970244+00:00",
    "generatedAt": "2025-10-02T02:04:28.968434+00:00",
    "summary": {
      "total": 8,
      "success": 7,
      "failed": 1
    },
    "benchmarkCount": 8,
    "failed": 1,
    "success": 7,
    "status": "needs_attention"
  },
  {
    "id": "6c3651d7-d8e5-405e-acd0-c6367caba435",
    "suite": "crisis",
    "requestedAt": "2025-10-02T02:04:27.034557+00:00",
    "generatedAt": "2025-10-02T02:04:27.033919+00:00",
    "summary": {
      "total": 1,
      "success": 0,
      "failed": 1
    },
    "benchmarkCount": 1,
    "failed": 1,
    "success": 0,
    "status": "needs_attention"
  },
  {
    "id": "6c183825-0b63-4282-af01-d8c0058cf1ac",
    "suite": "custom",
    "requestedAt": "2025-10-02T02:04:26.101098+00:00",
    "generatedAt": "2025-10-02T02:04:26.100295+00:00",
    "summary": {
      "total": 3,
      "success": 3,
      "failed": 0
    },
    "benchmarkCount": 3,
    "failed": 0,
    "success": 3,
    "status": "success"
  },
  {
    "id": "4f4b7c5b-b433-477b-9154-ceec022d774c",
    "suite": "output",
    "requestedAt": "2025-10-02T02:04:25.403219+00:00",
    "generatedAt": "2025-10-02T02:04:25.401092+00:00",
    "summary": {
      "total": 4,
      "success": 4,
      "failed": 0
    },
    "benchmarkCount": 4,
    "failed": 0,
    "success": 4,
    "status": "success"
  },
  {
    "id": "04d9b229-c069-4ece-9c6c-11b7418088cc",
    "suite": "output",
    "requestedAt": "2025-10-02T02:02:56.852133+00:00",
    "generatedAt": "2025-10-02T02:02:56.847849+00:00",
    "summary": {
      "total": 4,
      "success": 4,
      "failed": 0
    },
    "benchmarkCount": 4,
    "failed": 0,
    "success": 4,
    "status": "success"
  },
  {
    "id": "cbda0ee4-f66b-400a-8ff6-96a8b93ff109",
    "suite": "all",
    "requestedAt": "2025-10-02T02:01:55.411261+00:00",
    "generatedAt": "2025-10-02T02:01:55.409188+00:00",
    "summary": {
      "total": 8,
      "success": 7,
      "failed": 1
    },
    "benchmarkCount": 8,
    "failed": 1,
    "success": 7,
    "status": "needs_attention"
  },
  {
    "id": "02bcb348-7753-4056-8968-9fcb55f0ebbb",
    "suite": "output",
    "requestedAt": "2025-10-02T01:59:52.588778+00:00",
    "generatedAt": "2025-10-02T01:59:52.584164+00:00",
    "summary": {
      "total": 4,
      "success": 4,
      "failed": 0
    },
    "benchmarkCount": 4,
    "failed": 0,
    "success": 4,
    "status": "success"
  },
  {
    "id": "da0f4a8b-f184-40e6-ac78-0809355ede48",
    "suite": "output",
    "requestedAt": "2025-10-02T01:57:15.472553+00:00",
    "generatedAt": "2025-10-02T01:57:15.470484+00:00",
    "summary": {
      "total": 4,
      "success": 4,
      "failed": 0
    },
    "benchmarkCount": 4,
    "failed": 0,
    "success": 4,
    "status": "success"
  },
  {
    "id": "0f081d29-aa32-4986-a5cc-2940af2c364f",
    "suite": "output",
    "requestedAt": "2025-10-02T01:57:15.472166+00:00",
    "generatedAt": "2025-10-02T01:57:15.468952+00:00",
    "summary": {
      "total": 4,
      "success": 4,
      "failed": 0
    },
    "benchmarkCount": 4,
    "failed": 0,
    "success": 4,
    "status": "success"
  }
]